aiola_stt/__init__.py
aiola_stt/client.py
aiola_stt/config.py
aiola_stt/errors.py
aiola_stt-0.1.20.dist-info/METADATA
aiola_stt-0.1.20.dist-info/WHEEL
aiola_stt-0.1.20.dist-info/top_level.txt
aiola_stt-0.1.20.dist-info/RECORD
