Metadata-Version: 2.4
Name: aiola_stt
Version: 0.1.20
Summary: Aiola Speech-To-Text Python SDK
Author-email: "Gilad O." <gilad.or@aiola.com>, "Dor B." <dor.benatia@aiola.com>, "Ami V." <amichai.vaknin@aiola.com>
License-Expression: MIT
Project-URL: Homepage, https://aiola.ai/
Project-URL: Repository, https://github.com/aiola-lab/aiola-python-sdk.git
Requires-Python: >=3.8
Requires-Dist: websocket-client>=1.7.0
Requires-Dist: python-socketio>=5.8.0
Requires-Dist: websocket-client>=1.6.0
Requires-Dist: sounddevice>=0.4.6
Requires-Dist: python-dotenv>=1.0.0
Requires-Dist: pydantic>=2.0.0
Requires-Dist: requests>=2.31.0
Requires-Dist: numpy>=1.24.0
Requires-Dist: aiohttp>=3.8.0
Requires-Dist: aiofiles>=23.2.1
Requires-Dist: av>=10.0.0
Requires-Dist: soundfile>=0.12.1
Requires-Dist: scipy>=1.10.0
Provides-Extra: dev
Requires-Dist: pytest>=7.0.0; extra == "dev"
Requires-Dist: pytest-asyncio>=0.23.0; extra == "dev"
Requires-Dist: pytest-xdist>=3.0.0; extra == "dev"
Requires-Dist: pytest-forked>=1.4.0; extra == "dev"
Requires-Dist: pytest-cov>=4.0.0; extra == "dev"
Requires-Dist: black>=23.0.0; extra == "dev"
Requires-Dist: flake8>=6.0.0; extra == "dev"
Requires-Dist: mypy>=1.0.0; extra == "dev"
